{"cameraMode":{"drawMode":0,"name":"Shaded","section":"Shading Mode"},"sceneLighting":false,"audioPlay":false,"sceneViewState":{"showFog":true,"showMaterialUpdate":false,"showSkybox":false,"showFlares":true,"showImageEffects":true,"showParticleSystems":true},"in2DMode":false,"pivot":{"x":-0.10413646697998047,"y":0.5433312058448792,"z":-0.17042577266693116},"rotation":{"x":-0.045218877494335178,"y":-0.6377399563789368,"z":0.03754919767379761,"w":-0.768005907535553},"size":8.271742820739746,"orthographic":false}